[
  {
    "fileName": "1",
    "title": "Heaven of time",
    "desc": "Here he comes Here comes Speed Racer."
  },
  {
    "fileName": "2",
    "title": "Heaven of time",
    "desc": "Here he comes Here comes Speed Racer."
  },
  {
    "fileName": "3",
    "title": "Heaven of time",
    "desc": "Here he comes Here comes Speed Racer."
  },
  {
    "fileName": "4",
    "title": "Heaven of time",
    "desc": "Here he comes Here comes Speed Racer. "
  },
  {
    "fileName": "5",
    "title": "Heaven of time",
    "desc": "Here he comes Here comes Speed Racer. "
  },
  {
    "fileName": "6",
    "title": "Heaven of time",
    "desc": "Here he comes Here comes Speed Racer. "
  },
  {
    "fileName": "7",
    "title": "Heaven of time",
    "desc": "Here he comes Here comes Speed Racer. "
  },
  {
    "fileName": "8",
    "title": "Heaven of time",
    "desc": "Here he comes Here comes Speed Racer. "
  },
  {
    "fileName": "9",
    "title": "Heaven of time",
    "desc": "Here he comes Here comes Speed Racer. "
  },
  {
    "fileName": "10",
    "title": "Heaven of time",
    "desc": "Here he comes Here comes Speed Racer. "
  },
  {
    "fileName": "11",
    "title": "Heaven of time",
    "desc": "Here he comes Here comes Speed Racer. "
  },
  {
    "fileName": "12",
    "title": "Heaven of time",
    "desc": "Here he comes Here comes Speed Racer.  "
  },
  {
    "fileName": "13",
    "title": "Heaven of time",
    "desc": "Here he comes Here comes Speed Racer.  "
  },
  {
    "fileName": "14",
    "title": "Heaven of time",
    "desc": "Here he comes Here comes Speed Racer.  "
  },
  {
    "fileName": "15",
    "title": "Heaven of time",
    "desc": "Here he comes Here comes Speed Racer.  "
  },
  {
    "fileName": "16",
    "title": "Heaven of time",
    "desc": "Here he comes Here comes Speed Racer.  "
  }
]
